LICENSE
MANIFEST.in
README.md
setup.cfg
setup.py
versioneer.py
src/SensorNet.egg-info/PKG-INFO
src/SensorNet.egg-info/SOURCES.txt
src/SensorNet.egg-info/dependency_links.txt
src/SensorNet.egg-info/entry_points.txt
src/SensorNet.egg-info/not-zip-safe
src/SensorNet.egg-info/requires.txt
src/SensorNet.egg-info/top_level.txt
src/sensor_net/__init__.py
src/sensor_net/_ip_iterator.py
src/sensor_net/_logger.py
src/sensor_net/_plugin_loader.py
src/sensor_net/_run.py
src/sensor_net/_version.py
src/sensor_net/cmdline.py
src/sensor_net/config.py
src/sensor_net/cron.py
src/sensor_net/defaults.py
src/sensor_net/drivers.py
src/sensor_net/errors.py
src/sensor_net/types.py
src/sensor_net/backend_driver/__init__.py
src/sensor_net/backend_driver/stubber.py
src/sensor_net/backend_driver/sqlalchemy/__init__.py
src/sensor_net/backend_driver/sqlalchemy/_logger.py
src/sensor_net/backend_driver/sqlalchemy/config.py
src/sensor_net/backend_driver/sqlalchemy/driver.py
src/sensor_net/backend_driver/sqlalchemy/schema.py
src/sensor_net/sensor_driver/__init__.py
src/sensor_net/sensor_driver/base_http.py