Metadata-Version: 2.1
Name: SensorNet
Version: 1.0.post0.dev5
Summary: Daemon that will pull sensor data from a network of sensor hosting a micro HTTP API.
Home-page: https://github.com/HanaPoulpe/SensorNet
Author: Hana Burtin
Author-email: hana@hanaburtin.net
License: GPLv3
Keywords: Sensor,Networking
Platform: UNKNOWN
Classifier: Programming Language :: Python :: 3
Classifier: Programming Language :: Python :: 3.10
Classifier: Typing :: Typed
Classifier: Development Status :: 2 - Pre-Alpha
Classifier: Intended Audience :: Developers
Classifier: License :: OSI Approved :: GNU General Public License v3 (GPLv3)
Classifier: Natural Language :: English
Classifier: Operating System :: POSIX :: Linux
Classifier: Environment :: No Input/Output (Daemon)
Classifier: Topic :: System :: Monitoring
Classifier: Topic :: Utilities
Requires-Python: >=3.10
License-File: LICENSE
